[{"name":"should show logo","suite":"Header","result":"pass","start":1679058977129,"end":1679059002581,"duration":25452,"_type":"test","params":{"Device/Browser":"chrome"},"_Device/Browser Version":"111.0.5563.64"},{"name":"should show menu on menu icon click","suite":"Header","result":"pass","start":1679059002586,"end":1679059003741,"duration":1155,"_type":"test","params":{"Device/Browser":"chrome"},"_Device/Browser Version":"111.0.5563.64"},{"name":"should detect menu close button when element is clickable","suite":"Header","result":"pass","start":1679059003742,"end":1679059010441,"duration":6699,"_type":"test","params":{"Device/Browser":"chrome"},"_Device/Browser Version":"111.0.5563.64"}]